__init__.py
integra.py
integra-0.0.5.dist-info/LICENSE
integra-0.0.5.dist-info/METADATA
integra-0.0.5.dist-info/WHEEL
integra-0.0.5.dist-info/top_level.txt
integra-0.0.5.dist-info/RECORD
