Metadata-Version: 2.1
Name: integra
Version: 0.0.5
Summary: ZeroMQ Zeroconf RPC
Author-email: pmus <pmus.me@yandex.ru>
Project-URL: Homepage, https://github.com/pmus/integra
Classifier: Programming Language :: Python :: 3
Classifier: License :: OSI Approved :: MIT License
Classifier: Operating System :: OS Independent
Requires-Python: >=3.7
License-File: LICENSE
